[
  {
    "name": "Україна",
    "capital": "Київ",
    "region": "Європа"
  },
  {
    "name": "Сполучені Штати Америки",
    "capital": "Вашингтон, округ Колумбія",
    "region": "Північна Америка"
  },
  {
    "name": "Франція",
    "capital": "Париж",
    "region": "Європа"
  },
  {
    "name": "Китай",
    "capital": "Пекін",
    "region": "Азія"
  },
  {
    "name": "Бразилія",
    "capital": "Бразиліа",
    "region": "Південна Америка"
  },
  {
    "name": "Іспанія",
    "capital": "Мадрид",
    "region": "Європа"
  },
  {
    "name": "Росія",
    "capital": "Москва",
    "region": "Європа/Азія"
  },
  {
    "name": "Єгипет",
    "capital": "Каїр",
    "region": "Північна Африка"
  },
  {
    "name": "Австралія",
    "capital": "Канберра",
    "region": "Океанія"
  },
  {
    "name": "Італія",
    "capital": "Рим",
    "region": "Європа"
  }
]
